{
	"videos": [{
			"id": 1,
			"type": "header",
			"banner_url": "https://www.youtube.com/embed/t2xQasfL6z4"
		},
		{
			"id": 2,
			"type": "header",
			"banner_url": "https://www.youtube.com/embed/t2xQasfL6z4"
		},
		{
			"id": 3,
			"type": "header",
			"banner_url": "https://www.youtube.com/embed/t2xQasfL6z4"
		}
	],

	"banners": [{
			"id": 1,
			"type": "header",
			"landing_page": "https://dev.moladin.com/blog",
			"banner_url": "https://via.placeholder.com/1366x167.png"
		},
		{
			"id": 2,
			"type": "sidebar_opini_bikers",
			"landing_page": "https://dev.moladin.com/blog",
			"banner_url": "https://via.placeholder.com/488x203.png"
		},
		{
			"id": 3,
			"type": "sidebar_one",
			"landing_page": "https://dev.moladin.com/blog",
			"banner_url": "https://via.placeholder.com/488x203.png",
			"data": [{
					"id": 1,
					"landing_page": "https://dev.moladin.com/blog",
					"banner_url": "https://via.placeholder.com/238x198.png"
				},
				{
					"id": 2,
					"landing_page": "https://dev.moladin.com/blog",
					"banner_url": "https://via.placeholder.com/238x198.png"
				}
			]
		},
		{
			"id": 3,
			"type": "sidebar_two",
			"landing_page": "https://dev.moladin.com/blog",
			"banner_url": "https://via.placeholder.com/488x203.png",
			"data": [{
					"id": 1,
					"landing_page": "https://dev.moladin.com/blog",
					"banner_url": "https://via.placeholder.com/238x198.png"
				},
				{
					"id": 2,
					"landing_page": "https://dev.moladin.com/blog",
					"banner_url": "https://via.placeholder.com/238x198.png"
				}
			]
		},
		{
			"id": 4,
			"type": "sidebar_three",
			"landing_page": "https://dev.moladin.com/blog",
			"banner_url": "https://via.placeholder.com/488x203.png",
			"data": [{
					"id": 1,
					"landing_page": "https://dev.moladin.com/blog",
					"banner_url": "https://via.placeholder.com/238x198.png"
				},
				{
					"id": 2,
					"landing_page": "https://dev.moladin.com/blog",
					"banner_url": "https://via.placeholder.com/238x198.png"
				}
			]
		},
		{
			"id": 5,
			"type": "contents_ads_one",
			"data": [{
					"id": 1,
					"landing_page": "https://dev.moladin.com/blog",
					"banner_url": "https://via.placeholder.com/799x99.png"
				},
				{
					"id": 2,
					"landing_page": "https://dev.moladin.com/blog",
					"banner_url": "https://via.placeholder.com/799x99.png"
				}
			]
		},
		{
			"id": 6,
			"type": "contents_ads_two",
			"landing_page": "https://dev.moladin.com/blog",
			"banner_url": "https://via.placeholder.com/799x99.png"
		}
	]
}
